ytbot/__init__.py
ytbot/cfg.py
ytbot/master.py
ytbot/puppet.py
ytbot-0.2.10.dist-info/entry_points.txt
ytbot-0.2.10.dist-info/WHEEL
ytbot-0.2.10.dist-info/METADATA
ytbot-0.2.10.dist-info/RECORD
